ulowa/__init__.py
ulowa/ulowa.py
ulowa-1.1.0.dist-info/METADATA
ulowa-1.1.0.dist-info/WHEEL
ulowa-1.1.0.dist-info/top_level.txt
ulowa-1.1.0.dist-info/RECORD
