Metadata-Version: 2.1
Name: ulowa
Version: 1.1.0
Summary: Library for ULOWA operations, given fuzzy numbers
Home-page: https://github.com/imiguelrodriguez
Author: URV - GRUP ITAKA (Ignacio Miguel Rodríguez)
Author-email: ignacio.miguel@urv.cat
License: MIT
Platform: UNKNOWN
